{
    "parent": "minecraft:item/generated",
    "textures": {
        "layer0": "minecraft:item/leather_chestplate",
        "layer1": "minecraft:item/leather_chestplate_overlay"
    },
    "overrides": [
        {
            "predicate": {
                "damaged": 0,
                "damage": 0.0125,
                "custom_model_data": 0
            },
            "model": "luigis_mansion_dark_moon:entity/luigi/head"
        },
        {
            "predicate": {
                "damaged": 0,
                "damage": 0.025,
                "custom_model_data": 0
            },
            "model": "luigis_mansion_dark_moon:entity/luigi/right_arm"
        },
        {
            "predicate": {
                "damaged": 0,
                "damage": 0.0375,
                "custom_model_data": 0
            },
            "model": "luigis_mansion_dark_moon:entity/luigi/left_arm"
        },
        {
            "predicate": {
                "damaged": 0,
                "damage": 0.0125,
                "custom_model_data": 1
            },
            "model": "luigis_mansion_dark_moon:entity/luigi/body"
        },
        {
            "predicate": {
                "damaged": 0,
                "damage": 0.025,
                "custom_model_data": 1
            },
            "model": "luigis_mansion_dark_moon:entity/luigi/right_leg"
        },
        {
            "predicate": {
                "damaged": 0,
                "damage": 0.0375,
                "custom_model_data": 1
            },
            "model": "luigis_mansion_dark_moon:entity/luigi/left_leg"
        },
        {
            "predicate": {
                "damaged": 0,
                "damage": 0.0125,
                "custom_model_data": 2
            },
            "model": "luigis_mansion_dark_moon:entity/luigi/head_dead"
        },
        {
            "predicate": {
                "damaged": 0,
                "damage": 0.025,
                "custom_model_data": 2
            },
            "model": "luigis_mansion_dark_moon:entity/luigi/body_strobulbless_poltergust_right"
        },
        {
            "predicate": {
                "damaged": 0,
                "damage": 0.0375,
                "custom_model_data": 2
            },
            "model": "luigis_mansion_dark_moon:entity/luigi/body_strobulbless_poltergust_left"
        },
        {
            "predicate": {
                "damaged": 0,
                "damage": 0.025,
                "custom_model_data": 3
            },
            "model": "luigis_mansion_dark_moon:entity/luigi/body_strobulbless_poltergust_right_idle"
        },
        {
            "predicate": {
                "damaged": 0,
                "damage": 0.0375,
                "custom_model_data": 3
            },
            "model": "luigis_mansion_dark_moon:entity/luigi/body_strobulbless_poltergust_left_idle"
        },
        {
            "predicate": {
                "damaged": 0,
                "damage": 0.025,
                "custom_model_data": 4
            },
            "model": "luigis_mansion_dark_moon:entity/luigi/body_poltergust_right"
        },
        {
            "predicate": {
                "damaged": 0,
                "damage": 0.0375,
                "custom_model_data": 4
            },
            "model": "luigis_mansion_dark_moon:entity/luigi/body_poltergust_left"
        },
        {
            "predicate": {
                "damaged": 0,
                "damage": 0.025,
                "custom_model_data": 5
            },
            "model": "luigis_mansion_dark_moon:entity/luigi/body_poltergust_right_idle"
        },
        {
            "predicate": {
                "damaged": 0,
                "damage": 0.0375,
                "custom_model_data": 5
            },
            "model": "luigis_mansion_dark_moon:entity/luigi/body_poltergust_left_idle"
        },
        {
            "predicate": {
                "damaged": 0,
                "damage": 0.025,
                "custom_model_data": 6
            },
            "model": "luigis_mansion_dark_moon:entity/luigi/body_super_poltergust_right"
        },
        {
            "predicate": {
                "damaged": 0,
                "damage": 0.0375,
                "custom_model_data": 6
            },
            "model": "luigis_mansion_dark_moon:entity/luigi/body_super_poltergust_left"
        },
        {
            "predicate": {
                "damaged": 0,
                "damage": 0.025,
                "custom_model_data": 7
            },
            "model": "luigis_mansion_dark_moon:entity/luigi/body_super_poltergust_right_idle"
        },
        {
            "predicate": {
                "damaged": 0,
                "damage": 0.0375,
                "custom_model_data": 7
            },
            "model": "luigis_mansion_dark_moon:entity/luigi/body_super_poltergust_left_idle"
        },
        {
            "predicate": {
                "damaged": 0,
                "damage": 0.0125,
                "custom_model_data": 8
            },
            "model": "luigis_mansion_dark_moon:entity/luigi/head_2"
        },
        {
            "predicate": {
                "damaged": 0,
                "damage": 0.025,
                "custom_model_data": 8
            },
            "model": "luigis_mansion_dark_moon:entity/luigi/right_arm_2"
        },
        {
            "predicate": {
                "damaged": 0,
                "damage": 0.0375,
                "custom_model_data": 8
            },
            "model": "luigis_mansion_dark_moon:entity/luigi/left_arm_2"
        },
        {
            "predicate": {
                "damaged": 0,
                "damage": 0.0125,
                "custom_model_data": 9
            },
            "model": "luigis_mansion_dark_moon:entity/luigi/body_2"
        },
        {
            "predicate": {
                "damaged": 0,
                "damage": 0.025,
                "custom_model_data": 9
            },
            "model": "luigis_mansion_dark_moon:entity/luigi/right_leg_2"
        },
        {
            "predicate": {
                "damaged": 0,
                "damage": 0.0375,
                "custom_model_data": 9
            },
            "model": "luigis_mansion_dark_moon:entity/luigi/left_leg_2"
        },
        {
            "predicate": {
                "damaged": 0,
                "damage": 0.0125,
                "custom_model_data": 10
            },
            "model": "luigis_mansion_dark_moon:entity/luigi/head_dead_2"
        },
        {
            "predicate": {
                "damaged": 0,
                "damage": 0.025,
                "custom_model_data": 10
            },
            "model": "luigis_mansion_dark_moon:entity/luigi/body_strobulbless_poltergust_right_2"
        },
        {
            "predicate": {
                "damaged": 0,
                "damage": 0.0375,
                "custom_model_data": 10
            },
            "model": "luigis_mansion_dark_moon:entity/luigi/body_strobulbless_poltergust_left_2"
        },
        {
            "predicate": {
                "damaged": 0,
                "damage": 0.025,
                "custom_model_data": 11
            },
            "model": "luigis_mansion_dark_moon:entity/luigi/body_strobulbless_poltergust_right_idle_2"
        },
        {
            "predicate": {
                "damaged": 0,
                "damage": 0.0375,
                "custom_model_data": 11
            },
            "model": "luigis_mansion_dark_moon:entity/luigi/body_strobulbless_poltergust_left_idle_2"
        },
        {
            "predicate": {
                "damaged": 0,
                "damage": 0.025,
                "custom_model_data": 12
            },
            "model": "luigis_mansion_dark_moon:entity/luigi/body_poltergust_right_2"
        },
        {
            "predicate": {
                "damaged": 0,
                "damage": 0.0375,
                "custom_model_data": 12
            },
            "model": "luigis_mansion_dark_moon:entity/luigi/body_poltergust_left_2"
        },
        {
            "predicate": {
                "damaged": 0,
                "damage": 0.025,
                "custom_model_data": 13
            },
            "model": "luigis_mansion_dark_moon:entity/luigi/body_poltergust_right_idle_2"
        },
        {
            "predicate": {
                "damaged": 0,
                "damage": 0.0375,
                "custom_model_data": 13
            },
            "model": "luigis_mansion_dark_moon:entity/luigi/body_poltergust_left_idle_2"
        },
        {
            "predicate": {
                "damaged": 0,
                "damage": 0.025,
                "custom_model_data": 14
            },
            "model": "luigis_mansion_dark_moon:entity/luigi/body_super_poltergust_right_2"
        },
        {
            "predicate": {
                "damaged": 0,
                "damage": 0.0375,
                "custom_model_data": 14
            },
            "model": "luigis_mansion_dark_moon:entity/luigi/body_super_poltergust_left_2"
        },
        {
            "predicate": {
                "damaged": 0,
                "damage": 0.025,
                "custom_model_data": 15
            },
            "model": "luigis_mansion_dark_moon:entity/luigi/body_super_poltergust_right_idle_2"
        },
        {
            "predicate": {
                "damaged": 0,
                "damage": 0.0375,
                "custom_model_data": 15
            },
            "model": "luigis_mansion_dark_moon:entity/luigi/body_super_poltergust_left_idle_2"
        },
        {
            "predicate": {
                "damaged": 1
            },
            "model": "minecraft:item/leather_chestplate"
        }
    ]
}
